checkenv/__init__.py
checkenv/exceptions.py
checkenv-1.2.0.dist-info/LICENSE.md
checkenv-1.2.0.dist-info/METADATA
checkenv-1.2.0.dist-info/WHEEL
checkenv-1.2.0.dist-info/top_level.txt
checkenv-1.2.0.dist-info/RECORD
