Metadata-Version: 2.1
Name: checkenv
Version: 1.2.0
Summary: Ensures specified environment variables are present during runtime
Home-page: https://github.com/kylecaston/checkenv
Author: Kyle Caston
Author-email: kyle@caston.dev
License: UNKNOWN
Platform: UNKNOWN
Classifier: Programming Language :: Python :: 2.7
Classifier: Programming Language :: Python :: 3
Classifier: Programming Language :: Python :: 3.5
Classifier: Programming Language :: Python :: 3.6
Classifier: Programming Language :: Python :: 3.7
Classifier: Programming Language :: Python :: 3.8
Classifier: License :: OSI Approved :: MIT License
Classifier: Operating System :: OS Independent
Requires-Python: >=2.7, !=3.0.*, !=3.1.*, !=3.2.*, !=3.3.*, !=3.4.*, <4
Requires-Dist: jsonschema
Requires-Dist: colorama
Requires-Dist: future
